diffsync/__init__.py
diffsync/diff.py
diffsync/enum.py
diffsync/exceptions.py
diffsync/helpers.py
diffsync/log.py
diffsync/logging.py
diffsync/py.typed
diffsync/static/diffsync/docs/404.html
diffsync/static/diffsync/docs/admin/install.html
diffsync/static/diffsync/docs/admin/release_notes/index.html
diffsync/static/diffsync/docs/admin/release_notes/version_1.0.html
diffsync/static/diffsync/docs/admin/release_notes/version_1.1.html
diffsync/static/diffsync/docs/admin/release_notes/version_1.10.html
diffsync/static/diffsync/docs/admin/release_notes/version_1.2.html
diffsync/static/diffsync/docs/admin/release_notes/version_1.3.html
diffsync/static/diffsync/docs/admin/release_notes/version_1.4.html
diffsync/static/diffsync/docs/admin/release_notes/version_1.5.html
diffsync/static/diffsync/docs/admin/release_notes/version_1.6.html
diffsync/static/diffsync/docs/admin/release_notes/version_1.7.html
diffsync/static/diffsync/docs/admin/release_notes/version_1.8.html
diffsync/static/diffsync/docs/admin/release_notes/version_1.9.html
diffsync/static/diffsync/docs/admin/release_notes/version_2.0.html
diffsync/static/diffsync/docs/admin/release_notes/version_2.1.html
diffsync/static/diffsync/docs/admin/release_notes/version_2.2.html
diffsync/static/diffsync/docs/admin/uninstall.html
diffsync/static/diffsync/docs/admin/upgrade.html
diffsync/static/diffsync/docs/assets/_mkdocstrings.css
diffsync/static/diffsync/docs/assets/extra.css
diffsync/static/diffsync/docs/assets/favicon.ico
diffsync/static/diffsync/docs/assets/images/favicon.png
diffsync/static/diffsync/docs/assets/javascripts/bundle.56ea9cef.min.js
diffsync/static/diffsync/docs/assets/javascripts/bundle.56ea9cef.min.js.map
diffsync/static/diffsync/docs/assets/javascripts/glightbox.min.js
diffsync/static/diffsync/docs/assets/javascripts/lunr/min/lunr.ar.min.js
diffsync/static/diffsync/docs/assets/javascripts/lunr/min/lunr.da.min.js
diffsync/static/diffsync/docs/assets/javascripts/lunr/min/lunr.de.min.js
diffsync-2.2.0.dist-info/LICENSE
diffsync-2.2.0.dist-info/METADATA
diffsync-2.2.0.dist-info/WHEEL
diffsync-2.2.0.dist-info/RECORD
