Metadata-Version: 2.3
Name: diffsync
Version: 2.2.0
Summary: Library to easily sync/diff/update 2 different data sources
License: Apache-2.0
Keywords: source-of-truth,synchronization
Author: Network to Code, LLC
Author-email: info@networktocode.com
Requires-Python: >=3.10,<3.14
Classifier: Development Status :: 5 - Production/Stable
Classifier: Intended Audience :: Developers
Classifier: License :: OSI Approved :: Apache Software License
Classifier: Programming Language :: Python :: 3
Classifier: Programming Language :: Python :: 3.10
Classifier: Programming Language :: Python :: 3.11
Classifier: Programming Language :: Python :: 3.12
Classifier: Programming Language :: Python :: 3.13
Provides-Extra: redis
Requires-Dist: packaging (>=21.3)
Requires-Dist: pydantic (>=2.0.0,<3.0.0)
Requires-Dist: redis (>=4.3,<5.0) ; extra == "redis"
Requires-Dist: structlog (>=20.1.0)
Requires-Dist: typing-extensions (>=4.0.1) ; python_version < "3.11"
Project-URL: Documentation, https://diffsync.readthedocs.io
Project-URL: Homepage, https://diffsync.readthedocs.io
Project-URL: Repository, https://github.com/networktocode/diffsync
